Metadata-Version: 2.1
Name: ndtracker
Version: 1.0.2
Summary: High-frequency monitoring of neural network representational dimensionality
Author-email: Javier Marín <javier@jmarin.info>
License: MIT
Project-URL: Homepage, https://github.com/Javihaus/ndt
Project-URL: Documentation, https://ndt.readthedocs.io
Project-URL: Repository, https://github.com/Javihaus/ndt
Project-URL: Bug Tracker, https://github.com/Javihaus/ndt/issues
Classifier: Development Status :: 4 - Beta
Classifier: Intended Audience :: Science/Research
Classifier: Programming Language :: Python :: 3.8
Classifier: Programming Language :: Python :: 3.9
Classifier: Programming Language :: Python :: 3.10
Classifier: Programming Language :: Python :: 3.11
Classifier: Topic :: Scientific/Engineering :: Artificial Intelligence
Requires-Python: >=3.8
License-File: LICENSE
Requires-Dist: torch>=1.12.0
Requires-Dist: numpy>=1.21.0
Requires-Dist: pandas>=1.3.0
Requires-Dist: matplotlib>=3.5.0
Requires-Dist: seaborn>=0.11.0
Requires-Dist: plotly>=5.0.0
Requires-Dist: scipy>=1.7.0
Requires-Dist: tqdm>=4.62.0
Requires-Dist: pyyaml>=6.0
Requires-Dist: h5py>=3.6.0
Provides-Extra: dev
Requires-Dist: pytest>=7.0.0; extra == "dev"
Requires-Dist: pytest-cov>=3.0.0; extra == "dev"
Requires-Dist: black>=22.0.0; extra == "dev"
Requires-Dist: isort>=5.10.0; extra == "dev"
Requires-Dist: flake8>=4.0.0; extra == "dev"
Requires-Dist: mypy>=0.950; extra == "dev"
Provides-Extra: docs
Requires-Dist: mkdocs>=1.4.0; extra == "docs"
Requires-Dist: mkdocs-material>=8.5.0; extra == "docs"
Requires-Dist: mkdocstrings[python]>=0.19.0; extra == "docs"
Provides-Extra: jax
Requires-Dist: jax>=0.4.0; extra == "jax"
Requires-Dist: jaxlib>=0.4.0; extra == "jax"
